<?xml version="1.0" encoding="UTF-8" ?>
<!DOCTYPE struts PUBLIC
	"-//Apache Software Foundation//DTD Struts Configuration 2.3//EN"
	"http://struts.apache.org/dtds/struts-2.3.dtd">

<struts>
    <constant name="struts.multipart.maxSize" value="5500000000"/>
    <package name="default" namespace="/" extends="struts-default">
        <action name="login"  class="loginAction" >
           <result name="input">/login.jsp</result>
           <result name="success">/main.jsp</result>
        </action>
        
        
        <action name="search" class="searchAction" method="search">
        </action>
        
        <action name="showPicture" class="showPicturehAction">
            <result name="success">/showPicture.jsp</result>
        </action>
    </package>


</struts>
